<?xml version="1.0" encoding="UTF-8" ?>
<!DOCTYPE xliff PUBLIC "-//XLIFF//DTD XLIFF//EN" "http://www.oasis-open.org/committees/xliff/documents/xliff.dtd" >
<xliff version="1.0">
  <file original="global" source-language="en" datatype="plaintext">
    <header/>
    <body>
      <trans-unit>
        <source>Searching for "%s"</source>
        <target>Recherche pour "%s"</target>
      </trans-unit>
      <trans-unit>
        <source>Search Result</source>
        <target>Résultats de recherche</target>
      </trans-unit>
      <trans-unit>
        <source>Sympal Search / </source>
        <target>Recherche Sympal / </target>
      </trans-unit>
      <trans-unit>
        <source>Sympal Search</source>
        <target>Recherche Sympal</target>
      </trans-unit>
      <trans-unit>
        <source></source>
        <target></target>
      </trans-unit>
    </body>
  </file>
</xliff>
